avatar_emoji_bot/__init__.py
avatar_emoji_bot/__main__.py
avatar_emoji_bot/functions.py
avatar_emoji_bot/skill.py
avatar_emoji_bot/utils.py
avatar_emoji_bot-0.1.0.dist-info/METADATA
avatar_emoji_bot-0.1.0.dist-info/WHEEL
avatar_emoji_bot-0.1.0.dist-info/entry_points.txt
avatar_emoji_bot-0.1.0.dist-info/RECORD
