Metadata-Version: 2.4
Name: avatar-emoji-bot
Version: 0.1.0
Summary: Add your description here
Author-email: Artem Ivanov <art.ivanov@jetbrains.com>
Requires-Python: >=3.12
Requires-Dist: folds
Requires-Dist: pillow>=11.1.0
Requires-Dist: python-dotenv>=1.0.1
